CHANGES.rst
LICENSE.rst
LICENSE_GPL.rst
MANIFEST.in
README.rst
setup.py
src/bda/__init__.py
src/bda.plone.gtm.egg-info/PKG-INFO
src/bda.plone.gtm.egg-info/SOURCES.txt
src/bda.plone.gtm.egg-info/dependency_links.txt
src/bda.plone.gtm.egg-info/entry_points.txt
src/bda.plone.gtm.egg-info/namespace_packages.txt
src/bda.plone.gtm.egg-info/not-zip-safe
src/bda.plone.gtm.egg-info/requires.txt
src/bda.plone.gtm.egg-info/top_level.txt
src/bda/plone/__init__.py
src/bda/plone/gtm/__init__.py
src/bda/plone/gtm/configure.zcml
src/bda/plone/gtm/controlpanel.py
src/bda/plone/gtm/data.py
src/bda/plone/gtm/gtm_icon.png
src/bda/plone/gtm/interfaces.py
src/bda/plone/gtm/profiles.zcml
src/bda/plone/gtm/setuphandlers.py
src/bda/plone/gtm/viewlets.py
src/bda/plone/gtm/profiles/base/browserlayer.xml
src/bda/plone/gtm/profiles/base/controlpanel.xml
src/bda/plone/gtm/profiles/base/metadata.xml
src/bda/plone/gtm/profiles/base/registry.xml
src/bda/plone/gtm/profiles/plone4/metadata.xml
src/bda/plone/gtm/profiles/plone4/viewlets.xml
src/bda/plone/gtm/profiles/plone5/metadata.xml
src/bda/plone/gtm/profiles/plone5/viewlets.xml