Metadata-Version: 1.1
Name: bda.plone.gtm
Version: 1.0a1
Summary: Google Tag Manager Intergation
Home-page: UNKNOWN
Author: BlueDynamics Alliance
Author-email: dev@bluedynamics.com
License: GNU General Public Licence
Platform: UNKNOWN
Classifier: Environment :: Web Environment
Classifier: License :: OSI Approved :: GNU General Public License (GPL)
Classifier: Operating System :: OS Independent
Classifier: Programming Language :: Python
Classifier: Topic :: Software Development :: Libraries :: Python Modules
Classifier: Framework :: Plone :: 4.3
Classifier: Framework :: Plone :: 5.1
